{"paging":{"pageIndex":1,"pageSize":500,"total":17},"baseComponent":{"id":"AXldA-DFJy-qxChxiclj","key":"MatheusBlanco_2020.2-Eccoar_Gateway","name":"2020.2-Eccoar_Gateway","qualifier":"TRK","measures":[{"metric":"duplicated_lines_density","value":"0.0","bestValue":true},{"metric":"functions","value":"39"},{"metric":"test_execution_time","value":"80"},{"metric":"security_rating","value":"1.0","bestValue":true},{"metric":"tests","value":"9"},{"metric":"files","value":"8"},{"metric":"complexity","value":"40"},{"metric":"ncloc","value":"305"},{"metric":"coverage","value":"74.3","bestValue":false},{"metric":"reliability_rating","value":"1.0","bestValue":true},{"metric":"comment_lines_density","value":"0.0","bestValue":false},{"metric":"test_success_density","value":"100.0","bestValue":true}]},"components":[{"id":"AXll7YOQQg_XO-lMOfKt","key":"MatheusBlanco_2020.2-Eccoar_Gateway:src/api","name":"api","qualifier":"DIR","path":"src/api","measures":[{"metric":"duplicated_lines_density","value":"0.0","bestValue":true},{"metric":"functions","value":"23"},{"metric":"security_rating","value":"1.0","bestValue":true},{"metric":"files","value":"4"},{"metric":"complexity","value":"23"},{"metric":"ncloc","value":"187"},{"metric":"coverage","value":"59.3","bestValue":false},{"metric":"reliability_rating","value":"1.0","bestValue":true},{"metric":"comment_lines_density","value":"0.0","bestValue":false}]},{"id":"AXll7YOQQg_XO-lMOfKm","key":"MatheusBlanco_2020.2-Eccoar_Gateway:src/api/complaint","name":"complaint","qualifier":"DIR","path":"src/api/complaint","measures":[{"metric":"duplicated_lines_density","value":"0.0","bestValue":true},{"metric":"functions","value":"11"},{"metric":"security_rating","value":"1.0","bestValue":true},{"metric":"files","value":"1"},{"metric":"complexity","value":"11"},{"metric":"ncloc","value":"104"},{"metric":"coverage","value":"60.0","bestValue":false},{"metric":"reliability_rating","value":"1.0","bestValue":true},{"metric":"comment_lines_density","value":"0.0","bestValue":false}]},{"id":"AXll7YOQQg_XO-lMOfKl","key":"MatheusBlanco_2020.2-Eccoar_Gateway:src/api/complaint/ComplaintProxy.ts","name":"ComplaintProxy.ts","qualifier":"FIL","path":"src/api/complaint/ComplaintProxy.ts","language":"ts","measures":[{"metric":"complexity","value":"11"},{"metric":"functions","value":"11"},{"metric":"ncloc","value":"104"},{"metric":"coverage","value":"60.0","bestValue":false},{"metric":"reliability_rating","value":"1.0","bestValue":true},{"metric":"security_rating","value":"1.0","bestValue":true},{"metric":"comment_lines_density","value":"0.0","bestValue":false},{"metric":"files","value":"1"},{"metric":"duplicated_lines_density","value":"0.0","bestValue":true},{"metric":"test_success_density","value":"100.0","bestValue":true}]},{"id":"AXll7YOQQg_XO-lMOfKj","key":"MatheusBlanco_2020.2-Eccoar_Gateway:src/config","name":"config","qualifier":"DIR","path":"src/config","measures":[{"metric":"duplicated_lines_density","value":"0.0","bestValue":true},{"metric":"functions","value":"4"},{"metric":"security_rating","value":"1.0","bestValue":true},{"metric":"files","value":"2"},{"metric":"complexity","value":"4"},{"metric":"ncloc","value":"23"},{"metric":"coverage","value":"100.0","bestValue":true},{"metric":"reliability_rating","value":"1.0","bestValue":true},{"metric":"comment_lines_density","value":"0.0","bestValue":false}]},{"id":"AXll7YOQQg_XO-lMOfKi","key":"MatheusBlanco_2020.2-Eccoar_Gateway:src/config/enviroments.ts","name":"enviroments.ts","qualifier":"FIL","path":"src/config/enviroments.ts","language":"ts","measures":[{"metric":"complexity","value":"4"},{"metric":"functions","value":"4"},{"metric":"ncloc","value":"18"},{"metric":"coverage","value":"100.0","bestValue":true},{"metric":"reliability_rating","value":"1.0","bestValue":true},{"metric":"security_rating","value":"1.0","bestValue":true},{"metric":"comment_lines_density","value":"0.0","bestValue":false},{"metric":"files","value":"1"},{"metric":"duplicated_lines_density","value":"0.0","bestValue":true},{"metric":"test_success_density","value":"100.0","bestValue":true}]},{"id":"AXll7YOQQg_XO-lMOfKq","key":"MatheusBlanco_2020.2-Eccoar_Gateway:src/api/mailer","name":"mailer","qualifier":"DIR","path":"src/api/mailer","measures":[{"metric":"duplicated_lines_density","value":"0.0","bestValue":true},{"metric":"functions","value":"6"},{"metric":"security_rating","value":"1.0","bestValue":true},{"metric":"files","value":"1"},{"metric":"complexity","value":"6"},{"metric":"ncloc","value":"29"},{"metric":"coverage","value":"42.9","bestValue":false},{"metric":"reliability_rating","value":"1.0","bestValue":true},{"metric":"comment_lines_density","value":"0.0","bestValue":false}]},{"id":"AXll7YOQQg_XO-lMOfKp","key":"MatheusBlanco_2020.2-Eccoar_Gateway:src/api/mailer/MailerProxy.ts","name":"MailerProxy.ts","qualifier":"FIL","path":"src/api/mailer/MailerProxy.ts","language":"ts","measures":[{"metric":"complexity","value":"6"},{"metric":"functions","value":"6"},{"metric":"ncloc","value":"29"},{"metric":"coverage","value":"42.9","bestValue":false},{"metric":"reliability_rating","value":"1.0","bestValue":true},{"metric":"security_rating","value":"1.0","bestValue":true},{"metric":"comment_lines_density","value":"0.0","bestValue":false},{"metric":"files","value":"1"},{"metric":"duplicated_lines_density","value":"0.0","bestValue":true},{"metric":"test_success_density","value":"100.0","bestValue":true}]},{"id":"AXll7YOQQg_XO-lMOfKo","key":"MatheusBlanco_2020.2-Eccoar_Gateway:src/api/report","name":"report","qualifier":"DIR","path":"src/api/report","measures":[{"metric":"duplicated_lines_density","value":"0.0","bestValue":true},{"metric":"functions","value":"3"},{"metric":"security_rating","value":"1.0","bestValue":true},{"metric":"files","value":"1"},{"metric":"complexity","value":"3"},{"metric":"ncloc","value":"29"},{"metric":"coverage","value":"57.1","bestValue":false},{"metric":"reliability_rating","value":"1.0","bestValue":true},{"metric":"comment_lines_density","value":"0.0","bestValue":false}]},{"id":"AXll7YOQQg_XO-lMOfKn","key":"MatheusBlanco_2020.2-Eccoar_Gateway:src/api/report/ReportProxy.ts","name":"ReportProxy.ts","qualifier":"FIL","path":"src/api/report/ReportProxy.ts","language":"ts","measures":[{"metric":"complexity","value":"3"},{"metric":"functions","value":"3"},{"metric":"ncloc","value":"29"},{"metric":"coverage","value":"57.1","bestValue":false},{"metric":"reliability_rating","value":"1.0","bestValue":true},{"metric":"security_rating","value":"1.0","bestValue":true},{"metric":"comment_lines_density","value":"0.0","bestValue":false},{"metric":"files","value":"1"},{"metric":"duplicated_lines_density","value":"0.0","bestValue":true},{"metric":"test_success_density","value":"100.0","bestValue":true}]},{"id":"AXll7YOQQg_XO-lMOfKv","key":"MatheusBlanco_2020.2-Eccoar_Gateway:test/Routes.test.ts","name":"Routes.test.ts","qualifier":"UTS","path":"test/Routes.test.ts","language":"ts","measures":[{"metric":"test_execution_time","value":"80"},{"metric":"reliability_rating","value":"1.0","bestValue":true},{"metric":"tests","value":"9"},{"metric":"security_rating","value":"1.0","bestValue":true},{"metric":"duplicated_lines_density","value":"0.0","bestValue":true},{"metric":"test_success_density","value":"100.0","bestValue":true}]},{"id":"AXll7YOQQg_XO-lMOfKk","key":"MatheusBlanco_2020.2-Eccoar_Gateway:src/routes.ts","name":"routes.ts","qualifier":"FIL","path":"src/routes.ts","language":"ts","measures":[{"metric":"complexity","value":"11"},{"metric":"functions","value":"11"},{"metric":"ncloc","value":"59"},{"metric":"coverage","value":"78.3","bestValue":false},{"metric":"reliability_rating","value":"1.0","bestValue":true},{"metric":"security_rating","value":"1.0","bestValue":true},{"metric":"comment_lines_density","value":"0.0","bestValue":false},{"metric":"files","value":"1"},{"metric":"duplicated_lines_density","value":"0.0","bestValue":true},{"metric":"test_success_density","value":"100.0","bestValue":true}]},{"id":"AXll7YOQQg_XO-lMOfKh","key":"MatheusBlanco_2020.2-Eccoar_Gateway:src/config/sentry.ts","name":"sentry.ts","qualifier":"FIL","path":"src/config/sentry.ts","language":"ts","measures":[{"metric":"coverage","value":"100.0","bestValue":true},{"metric":"reliability_rating","value":"1.0","bestValue":true},{"metric":"complexity","value":"0"},{"metric":"functions","value":"0"},{"metric":"security_rating","value":"1.0","bestValue":true},{"metric":"comment_lines_density","value":"0.0","bestValue":false},{"metric":"ncloc","value":"5"},{"metric":"files","value":"1"},{"metric":"duplicated_lines_density","value":"0.0","bestValue":true},{"metric":"test_success_density","value":"100.0","bestValue":true}]},{"id":"AXll7YOQQg_XO-lMOfKg","key":"MatheusBlanco_2020.2-Eccoar_Gateway:src/server.ts","name":"server.ts","qualifier":"FIL","path":"src/server.ts","language":"ts","measures":[{"metric":"complexity","value":"2"},{"metric":"functions","value":"1"},{"metric":"ncloc","value":"36"},{"metric":"coverage","value":"100.0","bestValue":true},{"metric":"reliability_rating","value":"1.0","bestValue":true},{"metric":"security_rating","value":"1.0","bestValue":true},{"metric":"comment_lines_density","value":"0.0","bestValue":false},{"metric":"files","value":"1"},{"metric":"duplicated_lines_density","value":"0.0","bestValue":true},{"metric":"test_success_density","value":"100.0","bestValue":true}]},{"id":"AXll7YOQQg_XO-lMOfKu","key":"MatheusBlanco_2020.2-Eccoar_Gateway:src","name":"src","qualifier":"DIR","path":"src","measures":[{"metric":"duplicated_lines_density","value":"0.0","bestValue":true},{"metric":"functions","value":"39"},{"metric":"security_rating","value":"1.0","bestValue":true},{"metric":"files","value":"8"},{"metric":"complexity","value":"40"},{"metric":"ncloc","value":"305"},{"metric":"coverage","value":"74.3","bestValue":false},{"metric":"reliability_rating","value":"1.0","bestValue":true},{"metric":"comment_lines_density","value":"0.0","bestValue":false}]},{"id":"AXll7YOQQg_XO-lMOfKw","key":"MatheusBlanco_2020.2-Eccoar_Gateway:test","name":"test","qualifier":"DIR","path":"test","measures":[{"metric":"test_execution_time","value":"80"},{"metric":"reliability_rating","value":"1.0","bestValue":true},{"metric":"security_rating","value":"1.0","bestValue":true},{"metric":"test_success_density","value":"100.0","bestValue":true},{"metric":"tests","value":"9"}]},{"id":"AXll7YOQQg_XO-lMOfKs","key":"MatheusBlanco_2020.2-Eccoar_Gateway:src/api/users","name":"users","qualifier":"DIR","path":"src/api/users","measures":[{"metric":"duplicated_lines_density","value":"0.0","bestValue":true},{"metric":"functions","value":"3"},{"metric":"security_rating","value":"1.0","bestValue":true},{"metric":"files","value":"1"},{"metric":"complexity","value":"3"},{"metric":"ncloc","value":"25"},{"metric":"coverage","value":"76.9","bestValue":false},{"metric":"reliability_rating","value":"1.0","bestValue":true},{"metric":"comment_lines_density","value":"0.0","bestValue":false}]},{"id":"AXll7YOQQg_XO-lMOfKr","key":"MatheusBlanco_2020.2-Eccoar_Gateway:src/api/users/UsersProxy.ts","name":"UsersProxy.ts","qualifier":"FIL","path":"src/api/users/UsersProxy.ts","language":"ts","measures":[{"metric":"complexity","value":"3"},{"metric":"functions","value":"3"},{"metric":"ncloc","value":"25"},{"metric":"coverage","value":"76.9","bestValue":false},{"metric":"reliability_rating","value":"1.0","bestValue":true},{"metric":"security_rating","value":"1.0","bestValue":true},{"metric":"comment_lines_density","value":"0.0","bestValue":false},{"metric":"files","value":"1"},{"metric":"duplicated_lines_density","value":"0.0","bestValue":true},{"metric":"test_success_density","value":"100.0","bestValue":true}]}]}